<?xml version="1.0" encoding="utf-8"?>
<rule type="form" id="paycalendar_report" mode="on">
	<description>Отчеты - Платежный календарь</description>
	<xsltfile>forms/paycalendar_report.xsl</xsltfile>
	<doctype>main</doctype>
	<!-- <events>
		<queryopen source="file">form.airport.QueryOpen</queryopen>
		<querysave source="file">form.airport.QuerySave</querysave>
	</events>  -->
	<caption name="close" source="KEYWORD">Закрыть</caption>
	<caption name="properties" source="KEYWORD">Свойства</caption>
	<caption name="content" source="KEYWORD">Содержание</caption>
	<caption name="date" source="KEYWORD">дата</caption>
	<caption name="saved" source="KEYWORD">Сохраненный</caption>
	<caption name="newdoc" source="KEYWORD">Новый документ</caption>
	<caption name="editing" source="KEYWORD">Редактирование</caption>
	<caption name="readonly" source="KEYWORD">Только для чтения</caption>
	<caption name="modenotdefined" source="KEYWORD">Режим не определен</caption>
	<caption name="delattach" source="KEYWORD">Удалить</caption>
	<caption name="openattach" source="KEYWORD">Открыть</caption>
	<caption name="logout" source="KEYWORD">Завершить работу</caption>
	<caption name="cancel" source="KEYWORD">Отмена</caption>
	<caption name="changeview" source="KEYWORD">Изменить вид</caption>
	<caption name="commentcaption" source="KEYWORD">Комментарий</caption>
	<caption name="searchcaption" source="KEYWORD">поиск</caption>
	<caption name="additional" source="KEYWORD">Дополнительно</caption>
	<caption name="statusdoc" source="KEYWORD">Состояние документа</caption>
	<caption name="permissions" source="KEYWORD">Права доступа</caption>
	<caption name="infofread" source="KEYWORD">Информация о прочтении</caption>
	<caption name="infofreaders" source="KEYWORD">Кем прочтен</caption>
	<caption name="new" source="KEYWORD">Новое</caption>
	<caption name="category" source="KEYWORD">Категория</caption>
	<caption name="help" source="KEYWORD">Помощь</caption>
	<caption name="documentsavedcaption" source="KEYWORD">Документ сохранен</caption>
	<caption name="documentmarkread" source="KEYWORD">Документ отмечен как прочтенный</caption>
	<caption name="taskvn" source="KEYWORD">Номер</caption>
	<caption name="status" source="KEYWORD">Статус</caption>
	<caption name="dvn" source="KEYWORD">от</caption>
	<caption name="author" source="KEYWORD">Автор</caption>
	<caption name="comment" source="KEYWORD">Примечание</caption>
	<caption name="saving" source="KEYWORD">Сохранение</caption>
	<caption name="warning" source="KEYWORD">Предупреждение</caption>
	<caption name="whomread" source="KEYWORD">Кем прочтен</caption>
	<caption name="timeofreading" source="KEYWORD">Время прочтения</caption>
	<caption name="attention" source="KEYWORD">Внимание</caption>
	<caption name="add_comment" source="KEYWORD">Добавить комментарий</caption>
	<caption name="delete_file" source="KEYWORD">Удалить файл</caption>
	<caption name="comments" source="KEYWORD">комментарий</caption>
	<caption name ="view_userprofile" source ="KEYWORD">Посмотреть свойства текущего пользователя</caption>
	<caption name ="bin" source ="KEYWORD">БИН Коммунальных Гос. учреждений</caption>
	<caption name ="namerus" source ="KEYWORD">Наименование Гос. учреждения (рус.)</caption>
	<caption name ="namekaz" source ="KEYWORD">Наименование Гос. учреждения (каз.)</caption>
	<caption name ="contractnum" source ="KEYWORD">Номер договора</caption>
	<caption name ="balanceholder" source ="KEYWORD">Арендатор</caption>
	
	<caption name ="reportfiletype" source ="KEYWORD">Тип файла отчета</caption>
	<caption name ="propertytype" source ="KEYWORD">Тип имущества</caption>
	<caption name ="fillingreport" source ="KEYWORD">Сформировать отчет</caption>
	<caption name ="billboard" source ="KEYWORD">Биллборды</caption>
	<caption name ="columns" source ="KEYWORD">Электрические столбы</caption>
	<caption name ="electricnetworks" source ="KEYWORD">Электрические сети</caption>
	<caption name ="thermalnetworks" source ="KEYWORD">Тепловые сети</caption>
	<caption name ="gas" source ="KEYWORD">Газовые сети</caption>
	<caption name ="watersystem" source ="KEYWORD">Водопровод и канализация</caption>
	<caption name ="drain" source ="KEYWORD">Арычные сети</caption>
	<caption name ="road" source ="KEYWORD">Дороги</caption>
	<caption name ="parking" source ="KEYWORD">Парковки</caption>
</rule>
